readelf/__init__.py
readelf/const.py
readelf/elffile.py
readelf/err.py
readelf/header.py
readelf/helpers.py
readelf/maps.py
readelf/memory.py
readelf/sections.py
readelf/segments.py
readelf/parsers/__init__.py
readelf/parsers/dynamic.py
readelf/parsers/dynsym.py
readelf/parsers/rel.py
readelf/parsers/rela.py
readelf/parsers/section_parser.py
readelf/parsers/strtab.py
readelf/parsers/symtab.py
readelf-1.0.2.dist-info/licenses/LICENSE
readelf-1.0.2.dist-info/METADATA
readelf-1.0.2.dist-info/WHEEL
readelf-1.0.2.dist-info/top_level.txt
readelf-1.0.2.dist-info/RECORD
